XpiumLibraryFlutter/__init__.py
XpiumLibraryFlutter/main.py
XpiumLibraryFlutter/submodule1/__init__.py
XpiumLibraryFlutter/submodule1/module1.py
XpiumLibraryFlutter/submodule1/module2.py
XpiumLibraryFlutter/submodule2/__init__.py
XpiumLibraryFlutter/submodule2/module1.py
XpiumLibraryFlutter/submodule2/module2.py
XpiumLibraryFlutter-0.0.9.dist-info/LICENSE
XpiumLibraryFlutter-0.0.9.dist-info/METADATA
XpiumLibraryFlutter-0.0.9.dist-info/WHEEL
XpiumLibraryFlutter-0.0.9.dist-info/top_level.txt
XpiumLibraryFlutter-0.0.9.dist-info/RECORD
