Metadata-Version: 2.1
Name: XpiumLibraryFlutter
Version: 0.0.9
Summary: Test Library for XpiumLibraryFlutter
Home-page: https://github.com/tassh571/XpiumLibraryFlutter.git
Author: Tassana Khrueawan
Author-email: tassana.khr@gmail.com
Classifier: Programming Language :: Python :: 3
Classifier: License :: OSI Approved :: MIT License
Classifier: Operating System :: OS Independent
Requires-Python: >=3.6
License-File: LICENSE
Requires-Dist: robotframework >=3.0
